pipelane/__init__.py
pipelane/cli.py
pipelane/notification/__init__.py
pipelane/notification/main.py
pipelane-0.1.0.dist-info/METADATA
pipelane-0.1.0.dist-info/RECORD
pipelane-0.1.0.dist-info/WHEEL
pipelane-0.1.0.dist-info/entry_points.txt
pipelane-0.1.0.dist-info/top_level.txt
