Metadata-Version: 2.1
Name: pipelane
Version: 0.1.0
Summary: A small pipelane package
Home-page: https://github.com/lifuzu/pipelane
Author: Richard Li
Author-email: lifuzu+pipelane@gmail.com
License: UNKNOWN
Keywords: cli,pipelane,build system
Platform: UNKNOWN
Classifier: Programming Language :: Python :: 2.7
Classifier: License :: OSI Approved :: MIT License
Classifier: Operating System :: OS Independent
Requires-Dist: osascript (>=1.0.2)
